statute_matcher/__init__.py
statute_matcher/__main__.py
statute_matcher-0.0.3.dist-info/WHEEL
statute_matcher-0.0.3.dist-info/METADATA
statute_matcher-0.0.3.dist-info/RECORD
